{
  "term": "201708",
  "termName": "Fall 2017",
  "lastUpdated": "2026-01-11T11:10:37.616Z",
  "courses": {
    "CSE-6220": {
      "courseId": "CSE-6220",
      "subject": "CSE",
      "courseNumber": "6220",
      "name": "High Perform Computing",
      "creditHours": null,
      "sections": [
        {
          "crn": "88671",
          "sectionNumber": "O01",
          "instructor": "Vuduc, Richard",
          "enrolled": 126,
          "capacity": 250,
          "seatsAvailable": 124,
          "waitCount": 0,
          "waitCapacity": 200
        }
      ],
      "totalSeats": 250,
      "totalEnrolled": 126,
      "totalAvailable": 124,
      "totalWaitlisted": 0
    },
    "CSE-6242": {
      "courseId": "CSE-6242",
      "subject": "CSE",
      "courseNumber": "6242",
      "name": "Data &amp; Visual Analytics",
      "creditHours": null,
      "sections": [
        {
          "crn": "89699",
          "sectionNumber": "O01",
          "instructor": "Chakraborty, Arpan",
          "enrolled": 462,
          "capacity": 525,
          "seatsAvailable": 63,
          "waitCount": 0,
          "waitCapacity": 400
        }
      ],
      "totalSeats": 525,
      "totalEnrolled": 462,
      "totalAvailable": 63,
      "totalWaitlisted": 0
    },
    "CSE-6250": {
      "courseId": "CSE-6250",
      "subject": "CSE",
      "courseNumber": "6250",
      "name": "Big Data Health",
      "creditHours": null,
      "sections": [
        {
          "crn": "91341",
          "sectionNumber": "O01",
          "instructor": "Sun, Jimeng",
          "enrolled": 162,
          "capacity": 300,
          "seatsAvailable": 138,
          "waitCount": 0,
          "waitCapacity": 200
        }
      ],
      "totalSeats": 300,
      "totalEnrolled": 162,
      "totalAvailable": 138,
      "totalWaitlisted": 0
    },
    "CS-6035": {
      "courseId": "CS-6035",
      "subject": "CS",
      "courseNumber": "6035",
      "name": "Intro To Info Security",
      "creditHours": null,
      "sections": [
        {
          "crn": "88669",
          "sectionNumber": "O01",
          "instructor": "Lee, Wenke",
          "enrolled": 471,
          "capacity": 500,
          "seatsAvailable": 29,
          "waitCount": 0,
          "waitCapacity": 600
        }
      ],
      "totalSeats": 500,
      "totalEnrolled": 471,
      "totalAvailable": 29,
      "totalWaitlisted": 0
    },
    "CS-6210": {
      "courseId": "CS-6210",
      "subject": "CS",
      "courseNumber": "6210",
      "name": "Adv Operating Systems",
      "creditHours": null,
      "sections": [
        {
          "crn": "87895",
          "sectionNumber": "O01",
          "instructor": "Ramachandran, Umakishore",
          "enrolled": 158,
          "capacity": 300,
          "seatsAvailable": 142,
          "waitCount": 0,
          "waitCapacity": 250
        }
      ],
      "totalSeats": 300,
      "totalEnrolled": 158,
      "totalAvailable": 142,
      "totalWaitlisted": 0
    },
    "CS-6250": {
      "courseId": "CS-6250",
      "subject": "CS",
      "courseNumber": "6250",
      "name": "Computer Networks",
      "creditHours": null,
      "sections": [
        {
          "crn": "87896",
          "sectionNumber": "O01",
          "instructor": "Konte, Maria",
          "enrolled": 470,
          "capacity": 550,
          "seatsAvailable": 80,
          "waitCount": 0,
          "waitCapacity": 600
        }
      ],
      "totalSeats": 550,
      "totalEnrolled": 470,
      "totalAvailable": 80,
      "totalWaitlisted": 0
    },
    "CS-6262": {
      "courseId": "CS-6262",
      "subject": "CS",
      "courseNumber": "6262",
      "name": "Network Security",
      "creditHours": null,
      "sections": [
        {
          "crn": "89700",
          "sectionNumber": "O01",
          "instructor": "Lee, Wenke",
          "enrolled": 295,
          "capacity": 300,
          "seatsAvailable": 5,
          "waitCount": 0,
          "waitCapacity": 600
        }
      ],
      "totalSeats": 300,
      "totalEnrolled": 295,
      "totalAvailable": 5,
      "totalWaitlisted": 0
    },
    "CS-6290": {
      "courseId": "CS-6290",
      "subject": "CS",
      "courseNumber": "6290",
      "name": "High Perform Comput Arch",
      "creditHours": null,
      "sections": [
        {
          "crn": "87900",
          "sectionNumber": "O01",
          "instructor": "Prvulovic, Milos",
          "enrolled": 106,
          "capacity": 250,
          "seatsAvailable": 144,
          "waitCount": 0,
          "waitCapacity": 200
        }
      ],
      "totalSeats": 250,
      "totalEnrolled": 106,
      "totalAvailable": 144,
      "totalWaitlisted": 0
    },
    "CS-6300": {
      "courseId": "CS-6300",
      "subject": "CS",
      "courseNumber": "6300",
      "name": "Software Dev Process",
      "creditHours": null,
      "sections": [
        {
          "crn": "87897",
          "sectionNumber": "O01",
          "instructor": "Orso, Alessandro",
          "enrolled": 340,
          "capacity": 350,
          "seatsAvailable": 10,
          "waitCount": 0,
          "waitCapacity": 600
        }
      ],
      "totalSeats": 350,
      "totalEnrolled": 340,
      "totalAvailable": 10,
      "totalWaitlisted": 0
    },
    "CS-6310": {
      "courseId": "CS-6310",
      "subject": "CS",
      "courseNumber": "6310",
      "name": "Software Arch &amp; Design",
      "creditHours": null,
      "sections": [
        {
          "crn": "87901",
          "sectionNumber": "O01",
          "instructor": "Moss, Mark",
          "enrolled": 313,
          "capacity": 424,
          "seatsAvailable": 111,
          "waitCount": 0,
          "waitCapacity": 450
        }
      ],
      "totalSeats": 424,
      "totalEnrolled": 313,
      "totalAvailable": 111,
      "totalWaitlisted": 0
    },
    "CS-6340": {
      "courseId": "CS-6340",
      "subject": "CS",
      "courseNumber": "6340",
      "name": "Software Analysis &amp; Test",
      "creditHours": null,
      "sections": [
        {
          "crn": "89694",
          "sectionNumber": "O01",
          "instructor": "Naik, Mayur",
          "enrolled": 182,
          "capacity": 250,
          "seatsAvailable": 68,
          "waitCount": 0,
          "waitCapacity": 400
        }
      ],
      "totalSeats": 250,
      "totalEnrolled": 182,
      "totalAvailable": 68,
      "totalWaitlisted": 0
    },
    "CS-6400": {
      "courseId": "CS-6400",
      "subject": "CS",
      "courseNumber": "6400",
      "name": "DB Sys Concepts&amp; Design",
      "creditHours": null,
      "sections": [
        {
          "crn": "89695",
          "sectionNumber": "O01",
          "instructor": "Mark, Leo",
          "enrolled": 413,
          "capacity": 450,
          "seatsAvailable": 37,
          "waitCount": 0,
          "waitCapacity": 600
        }
      ],
      "totalSeats": 450,
      "totalEnrolled": 413,
      "totalAvailable": 37,
      "totalWaitlisted": 0
    },
    "CS-6440": {
      "courseId": "CS-6440",
      "subject": "CS",
      "courseNumber": "6440",
      "name": "Intro Health Informatics",
      "creditHours": null,
      "sections": [
        {
          "crn": "87902",
          "sectionNumber": "O01",
          "instructor": "Braunstein, Mark",
          "enrolled": 244,
          "capacity": 250,
          "seatsAvailable": 6,
          "waitCount": 0,
          "waitCapacity": 600
        }
      ],
      "totalSeats": 250,
      "totalEnrolled": 244,
      "totalAvailable": 6,
      "totalWaitlisted": 0
    },
    "CS-6460": {
      "courseId": "CS-6460",
      "subject": "CS",
      "courseNumber": "6460",
      "name": "Educ Tech-Foundations",
      "creditHours": null,
      "sections": [
        {
          "crn": "88963",
          "sectionNumber": "O01",
          "instructor": "Joyner, David",
          "enrolled": 228,
          "capacity": 262,
          "seatsAvailable": 34,
          "waitCount": 0,
          "waitCapacity": 400
        }
      ],
      "totalSeats": 262,
      "totalEnrolled": 228,
      "totalAvailable": 34,
      "totalWaitlisted": 0
    },
    "CS-6475": {
      "courseId": "CS-6475",
      "subject": "CS",
      "courseNumber": "6475",
      "name": "Comp. Photography",
      "creditHours": null,
      "sections": [
        {
          "crn": "88667",
          "sectionNumber": "O01",
          "instructor": "Essa, Irfan",
          "enrolled": 281,
          "capacity": 400,
          "seatsAvailable": 119,
          "waitCount": 0,
          "waitCapacity": 450
        }
      ],
      "totalSeats": 400,
      "totalEnrolled": 281,
      "totalAvailable": 119,
      "totalWaitlisted": 0
    },
    "CS-6476": {
      "courseId": "CS-6476",
      "subject": "CS",
      "courseNumber": "6476",
      "name": "Computer Vision",
      "creditHours": null,
      "sections": [
        {
          "crn": "88939",
          "sectionNumber": "O01",
          "instructor": "Essa, Irfan",
          "enrolled": 337,
          "capacity": 418,
          "seatsAvailable": 81,
          "waitCount": 0,
          "waitCapacity": 600
        }
      ],
      "totalSeats": 418,
      "totalEnrolled": 337,
      "totalAvailable": 81,
      "totalWaitlisted": 0
    },
    "CS-6601": {
      "courseId": "CS-6601",
      "subject": "CS",
      "courseNumber": "6601",
      "name": "Artificial Intelligence",
      "creditHours": null,
      "sections": [
        {
          "crn": "89696",
          "sectionNumber": "O01",
          "instructor": "Starner, Thad",
          "enrolled": 399,
          "capacity": 500,
          "seatsAvailable": 101,
          "waitCount": 0,
          "waitCapacity": 600
        }
      ],
      "totalSeats": 500,
      "totalEnrolled": 399,
      "totalAvailable": 101,
      "totalWaitlisted": 0
    },
    "CS-6750": {
      "courseId": "CS-6750",
      "subject": "CS",
      "courseNumber": "6750",
      "name": "Human-Computer Interact",
      "creditHours": null,
      "sections": [
        {
          "crn": "90326",
          "sectionNumber": "O01",
          "instructor": "Joyner, David",
          "enrolled": 242,
          "capacity": 300,
          "seatsAvailable": 58,
          "waitCount": 0,
          "waitCapacity": 400
        }
      ],
      "totalSeats": 300,
      "totalEnrolled": 242,
      "totalAvailable": 58,
      "totalWaitlisted": 0
    },
    "CS-6999": {
      "courseId": "CS-6999",
      "subject": "CS",
      "courseNumber": "6999",
      "name": "Master&#39;s Project",
      "creditHours": null,
      "sections": [
        {
          "crn": "85665",
          "sectionNumber": "O01",
          "instructor": "Omiecinski, Edward",
          "enrolled": 0,
          "capacity": 5,
          "seatsAvailable": 5,
          "waitCount": 0,
          "waitCapacity": 0
        },
        {
          "crn": "85666",
          "sectionNumber": "O02",
          "instructor": "Orso, Alessandro",
          "enrolled": 1,
          "capacity": 5,
          "seatsAvailable": 4,
          "waitCount": 0,
          "waitCapacity": 0
        }
      ],
      "totalSeats": 10,
      "totalEnrolled": 1,
      "totalAvailable": 9,
      "totalWaitlisted": 0
    },
    "CS-7637": {
      "courseId": "CS-7637",
      "subject": "CS",
      "courseNumber": "7637",
      "name": "Knowledge-Based AI",
      "creditHours": null,
      "sections": [
        {
          "crn": "87904",
          "sectionNumber": "O01",
          "instructor": "Goel, Ashok",
          "enrolled": 332,
          "capacity": 450,
          "seatsAvailable": 118,
          "waitCount": 0,
          "waitCapacity": 600
        }
      ],
      "totalSeats": 450,
      "totalEnrolled": 332,
      "totalAvailable": 118,
      "totalWaitlisted": 0
    },
    "CS-7641": {
      "courseId": "CS-7641",
      "subject": "CS",
      "courseNumber": "7641",
      "name": "Machine Learning",
      "creditHours": null,
      "sections": [
        {
          "crn": "87898",
          "sectionNumber": "O01",
          "instructor": "Isbell, Charles",
          "enrolled": 582,
          "capacity": 600,
          "seatsAvailable": 18,
          "waitCount": 0,
          "waitCapacity": 600
        }
      ],
      "totalSeats": 600,
      "totalEnrolled": 582,
      "totalAvailable": 18,
      "totalWaitlisted": 0
    },
    "CS-7642": {
      "courseId": "CS-7642",
      "subject": "CS",
      "courseNumber": "7642",
      "name": "Reinforcement Learning",
      "creditHours": null,
      "sections": [
        {
          "crn": "91769",
          "sectionNumber": "O03",
          "instructor": "Isbell, Charles",
          "enrolled": 211,
          "capacity": 350,
          "seatsAvailable": 139,
          "waitCount": 0,
          "waitCapacity": 400
        }
      ],
      "totalSeats": 350,
      "totalEnrolled": 211,
      "totalAvailable": 139,
      "totalWaitlisted": 0
    },
    "CS-7646": {
      "courseId": "CS-7646",
      "subject": "CS",
      "courseNumber": "7646",
      "name": "Mach Learn For Trading",
      "creditHours": null,
      "sections": [
        {
          "crn": "90234",
          "sectionNumber": "O01",
          "instructor": "Balch, Tucker",
          "enrolled": 689,
          "capacity": 700,
          "seatsAvailable": 11,
          "waitCount": 0,
          "waitCapacity": 600
        }
      ],
      "totalSeats": 700,
      "totalEnrolled": 689,
      "totalAvailable": 11,
      "totalWaitlisted": 0
    },
    "CS-8803-O01": {
      "courseId": "CS-8803-O01",
      "subject": "CS",
      "courseNumber": "8803-O01",
      "name": "Special Topics",
      "creditHours": null,
      "sections": [
        {
          "crn": "87899",
          "sectionNumber": "O01",
          "instructor": "Thrun, Sebastian",
          "enrolled": 277,
          "capacity": 400,
          "seatsAvailable": 123,
          "waitCount": 0,
          "waitCapacity": 400
        }
      ],
      "totalSeats": 400,
      "totalEnrolled": 277,
      "totalAvailable": 123,
      "totalWaitlisted": 0
    },
    "CS-8803-O02": {
      "courseId": "CS-8803-O02",
      "subject": "CS",
      "courseNumber": "8803-O02",
      "name": "Special Topics",
      "creditHours": null,
      "sections": [
        {
          "crn": "88668",
          "sectionNumber": "O02",
          "instructor": "Gavrilovska, Ada",
          "enrolled": 294,
          "capacity": 350,
          "seatsAvailable": 56,
          "waitCount": 0,
          "waitCapacity": 400
        }
      ],
      "totalSeats": 350,
      "totalEnrolled": 294,
      "totalAvailable": 56,
      "totalWaitlisted": 0
    },
    "CS-8803-O04": {
      "courseId": "CS-8803-O04",
      "subject": "CS",
      "courseNumber": "8803-O04",
      "name": "Special Topics",
      "creditHours": null,
      "sections": [
        {
          "crn": "89697",
          "sectionNumber": "O04",
          "instructor": "Pande, Santosh",
          "enrolled": 41,
          "capacity": 250,
          "seatsAvailable": 209,
          "waitCount": 0,
          "waitCapacity": 200
        }
      ],
      "totalSeats": 250,
      "totalEnrolled": 41,
      "totalAvailable": 209,
      "totalWaitlisted": 0
    },
    "CS-8803-O07": {
      "courseId": "CS-8803-O07",
      "subject": "CS",
      "courseNumber": "8803-O07",
      "name": "Special Topics",
      "creditHours": null,
      "sections": [
        {
          "crn": "89969",
          "sectionNumber": "O07",
          "instructor": "Beyah, Raheem",
          "enrolled": 103,
          "capacity": 250,
          "seatsAvailable": 147,
          "waitCount": 0,
          "waitCapacity": 100
        }
      ],
      "totalSeats": 250,
      "totalEnrolled": 103,
      "totalAvailable": 147,
      "totalWaitlisted": 0
    },
    "CS-8803-O08": {
      "courseId": "CS-8803-O08",
      "subject": "CS",
      "courseNumber": "8803-O08",
      "name": "Special Topics",
      "creditHours": null,
      "sections": [
        {
          "crn": "91347",
          "sectionNumber": "O08",
          "instructor": "Pande, Santosh",
          "enrolled": 47,
          "capacity": 250,
          "seatsAvailable": 203,
          "waitCount": 0,
          "waitCapacity": 200
        }
      ],
      "totalSeats": 250,
      "totalEnrolled": 47,
      "totalAvailable": 203,
      "totalWaitlisted": 0
    },
    "CS-8803-O09": {
      "courseId": "CS-8803-O09",
      "subject": "CS",
      "courseNumber": "8803-O09",
      "name": "Special Topics",
      "creditHours": null,
      "sections": [
        {
          "crn": "91349",
          "sectionNumber": "O09",
          "instructor": "Feron, Eric",
          "enrolled": 34,
          "capacity": 250,
          "seatsAvailable": 216,
          "waitCount": 0,
          "waitCapacity": 200
        }
      ],
      "totalSeats": 250,
      "totalEnrolled": 34,
      "totalAvailable": 216,
      "totalWaitlisted": 0
    },
    "CS-8903": {
      "courseId": "CS-8903",
      "subject": "CS",
      "courseNumber": "8903",
      "name": "Special Problems",
      "creditHours": null,
      "sections": [
        {
          "crn": "80212",
          "sectionNumber": "O01",
          "instructor": "Omiecinski, Edward",
          "enrolled": 0,
          "capacity": 15,
          "seatsAvailable": 15,
          "waitCount": 0,
          "waitCapacity": 0
        },
        {
          "crn": "82653",
          "sectionNumber": "O02",
          "instructor": "Orso, Alessandro",
          "enrolled": 0,
          "capacity": 15,
          "seatsAvailable": 15,
          "waitCount": 0,
          "waitCapacity": 0
        }
      ],
      "totalSeats": 30,
      "totalEnrolled": 0,
      "totalAvailable": 30,
      "totalWaitlisted": 0
    },
    "CS-8999": {
      "courseId": "CS-8999",
      "subject": "CS",
      "courseNumber": "8999",
      "name": "Doctoral Thesis Prep",
      "creditHours": null,
      "sections": [
        {
          "crn": "84694",
          "sectionNumber": "O02",
          "instructor": "Orso, Alessandro",
          "enrolled": 4,
          "capacity": 15,
          "seatsAvailable": 11,
          "waitCount": 0,
          "waitCapacity": 0
        }
      ],
      "totalSeats": 15,
      "totalEnrolled": 4,
      "totalAvailable": 11,
      "totalWaitlisted": 0
    },
    "CS-9000": {
      "courseId": "CS-9000",
      "subject": "CS",
      "courseNumber": "9000",
      "name": "Doctoral Thesis",
      "creditHours": null,
      "sections": [
        {
          "crn": "82683",
          "sectionNumber": "O02",
          "instructor": "Orso, Alessandro",
          "enrolled": 3,
          "capacity": 15,
          "seatsAvailable": 12,
          "waitCount": 0,
          "waitCapacity": 0
        }
      ],
      "totalSeats": 15,
      "totalEnrolled": 3,
      "totalAvailable": 12,
      "totalWaitlisted": 0
    },
    "ECE-7000": {
      "courseId": "ECE-7000",
      "subject": "ECE",
      "courseNumber": "7000",
      "name": "Master&#39;s Thesis",
      "creditHours": null,
      "sections": [
        {
          "crn": "81842",
          "sectionNumber": "O01",
          "instructor": "Owen, Henry",
          "enrolled": 0,
          "capacity": 5,
          "seatsAvailable": 5,
          "waitCount": 0,
          "waitCapacity": 0
        }
      ],
      "totalSeats": 5,
      "totalEnrolled": 0,
      "totalAvailable": 5,
      "totalWaitlisted": 0
    },
    "ECE-8900": {
      "courseId": "ECE-8900",
      "subject": "ECE",
      "courseNumber": "8900",
      "name": "Special Problems",
      "creditHours": null,
      "sections": [
        {
          "crn": "83493",
          "sectionNumber": "O01",
          "instructor": "Owen, Henry",
          "enrolled": 0,
          "capacity": 25,
          "seatsAvailable": 25,
          "waitCount": 0,
          "waitCapacity": 0
        },
        {
          "crn": "83495",
          "sectionNumber": "O02",
          "instructor": "Ougazzaden, Abdallah",
          "enrolled": 0,
          "capacity": 10,
          "seatsAvailable": 10,
          "waitCount": 0,
          "waitCapacity": 0
        }
      ],
      "totalSeats": 35,
      "totalEnrolled": 0,
      "totalAvailable": 35,
      "totalWaitlisted": 0
    },
    "ECE-8903": {
      "courseId": "ECE-8903",
      "subject": "ECE",
      "courseNumber": "8903",
      "name": "Special Problems",
      "creditHours": 3,
      "sections": [
        {
          "crn": "81135",
          "sectionNumber": "O01",
          "instructor": "Owen, Henry",
          "enrolled": 0,
          "capacity": 15,
          "seatsAvailable": 15,
          "waitCount": 0,
          "waitCapacity": 0
        }
      ],
      "totalSeats": 15,
      "totalEnrolled": 0,
      "totalAvailable": 15,
      "totalWaitlisted": 0
    },
    "ECE-9000": {
      "courseId": "ECE-9000",
      "subject": "ECE",
      "courseNumber": "9000",
      "name": "Doctoral Thesis",
      "creditHours": null,
      "sections": [
        {
          "crn": "81018",
          "sectionNumber": "O01",
          "instructor": "Owen, Henry",
          "enrolled": 1,
          "capacity": 25,
          "seatsAvailable": 24,
          "waitCount": 0,
          "waitCapacity": 0
        },
        {
          "crn": "83279",
          "sectionNumber": "O02",
          "instructor": "Ougazzaden, Abdallah",
          "enrolled": 0,
          "capacity": 15,
          "seatsAvailable": 15,
          "waitCount": 0,
          "waitCapacity": 0
        }
      ],
      "totalSeats": 40,
      "totalEnrolled": 1,
      "totalAvailable": 39,
      "totalWaitlisted": 0
    }
  }
}