{
  "term": "201802",
  "termName": "Spring 2018",
  "lastUpdated": "2026-01-11T11:08:50.721Z",
  "courses": {
    "CSE-6220": {
      "courseId": "CSE-6220",
      "subject": "CSE",
      "courseNumber": "6220",
      "name": "High Perform Computing",
      "creditHours": null,
      "sections": [
        {
          "crn": "28350",
          "sectionNumber": "O01",
          "instructor": "Vuduc, Richard",
          "enrolled": 109,
          "capacity": 173,
          "seatsAvailable": 64,
          "waitCount": 0,
          "waitCapacity": 500
        }
      ],
      "totalSeats": 173,
      "totalEnrolled": 109,
      "totalAvailable": 64,
      "totalWaitlisted": 0
    },
    "CSE-6242": {
      "courseId": "CSE-6242",
      "subject": "CSE",
      "courseNumber": "6242",
      "name": "Data &amp; Visual Analytics",
      "creditHours": null,
      "sections": [
        {
          "crn": "29568",
          "sectionNumber": "O01",
          "instructor": "Chakraborty, Arpan",
          "enrolled": 591,
          "capacity": 650,
          "seatsAvailable": 59,
          "waitCount": 0,
          "waitCapacity": 500
        }
      ],
      "totalSeats": 650,
      "totalEnrolled": 591,
      "totalAvailable": 59,
      "totalWaitlisted": 0
    },
    "CSE-6250": {
      "courseId": "CSE-6250",
      "subject": "CSE",
      "courseNumber": "6250",
      "name": "Big Data Health",
      "creditHours": null,
      "sections": [
        {
          "crn": "29922",
          "sectionNumber": "O01",
          "instructor": "Sun, Jimeng",
          "enrolled": 166,
          "capacity": 250,
          "seatsAvailable": 84,
          "waitCount": 0,
          "waitCapacity": 500
        }
      ],
      "totalSeats": 250,
      "totalEnrolled": 166,
      "totalAvailable": 84,
      "totalWaitlisted": 0
    },
    "CS-6035": {
      "courseId": "CS-6035",
      "subject": "CS",
      "courseNumber": "6035",
      "name": "Intro To Info Security",
      "creditHours": null,
      "sections": [
        {
          "crn": "28332",
          "sectionNumber": "O01",
          "instructor": "Lee, Wenke",
          "enrolled": 519,
          "capacity": 600,
          "seatsAvailable": 81,
          "waitCount": 0,
          "waitCapacity": 500
        }
      ],
      "totalSeats": 600,
      "totalEnrolled": 519,
      "totalAvailable": 81,
      "totalWaitlisted": 0
    },
    "CS-6200": {
      "courseId": "CS-6200",
      "subject": "CS",
      "courseNumber": "6200",
      "name": "Graduate Intro to OS",
      "creditHours": null,
      "sections": [
        {
          "crn": "31243",
          "sectionNumber": "O01",
          "instructor": "Gavrilovska, Ada",
          "enrolled": 407,
          "capacity": 500,
          "seatsAvailable": 93,
          "waitCount": 0,
          "waitCapacity": 500
        }
      ],
      "totalSeats": 500,
      "totalEnrolled": 407,
      "totalAvailable": 93,
      "totalWaitlisted": 0
    },
    "CS-6210": {
      "courseId": "CS-6210",
      "subject": "CS",
      "courseNumber": "6210",
      "name": "Adv Operating Systems",
      "creditHours": null,
      "sections": [
        {
          "crn": "26604",
          "sectionNumber": "O01",
          "instructor": "Ramachandran, Umakishore",
          "enrolled": 110,
          "capacity": 300,
          "seatsAvailable": 190,
          "waitCount": 0,
          "waitCapacity": 500
        }
      ],
      "totalSeats": 300,
      "totalEnrolled": 110,
      "totalAvailable": 190,
      "totalWaitlisted": 0
    },
    "CS-6250": {
      "courseId": "CS-6250",
      "subject": "CS",
      "courseNumber": "6250",
      "name": "Computer Networks",
      "creditHours": null,
      "sections": [
        {
          "crn": "26605",
          "sectionNumber": "O01",
          "instructor": "Konte, Maria",
          "enrolled": 435,
          "capacity": 550,
          "seatsAvailable": 115,
          "waitCount": 0,
          "waitCapacity": 500
        }
      ],
      "totalSeats": 550,
      "totalEnrolled": 435,
      "totalAvailable": 115,
      "totalWaitlisted": 0
    },
    "CS-6262": {
      "courseId": "CS-6262",
      "subject": "CS",
      "courseNumber": "6262",
      "name": "Network Security",
      "creditHours": null,
      "sections": [
        {
          "crn": "29569",
          "sectionNumber": "O01",
          "instructor": "Lee, Wenke",
          "enrolled": 326,
          "capacity": 400,
          "seatsAvailable": 74,
          "waitCount": 0,
          "waitCapacity": 500
        }
      ],
      "totalSeats": 400,
      "totalEnrolled": 326,
      "totalAvailable": 74,
      "totalWaitlisted": 0
    },
    "CS-6290": {
      "courseId": "CS-6290",
      "subject": "CS",
      "courseNumber": "6290",
      "name": "High Perform Comput Arch",
      "creditHours": null,
      "sections": [
        {
          "crn": "27257",
          "sectionNumber": "O01",
          "instructor": "Prvulovic, Milos",
          "enrolled": 132,
          "capacity": 300,
          "seatsAvailable": 168,
          "waitCount": 0,
          "waitCapacity": 500
        }
      ],
      "totalSeats": 300,
      "totalEnrolled": 132,
      "totalAvailable": 168,
      "totalWaitlisted": 0
    },
    "CS-6291": {
      "courseId": "CS-6291",
      "subject": "CS",
      "courseNumber": "6291",
      "name": "Embedded Software Opt.",
      "creditHours": null,
      "sections": [
        {
          "crn": "31244",
          "sectionNumber": "O01",
          "instructor": "Pande, Santosh",
          "enrolled": 86,
          "capacity": 200,
          "seatsAvailable": 114,
          "waitCount": 0,
          "waitCapacity": 500
        }
      ],
      "totalSeats": 200,
      "totalEnrolled": 86,
      "totalAvailable": 114,
      "totalWaitlisted": 0
    },
    "CS-6300": {
      "courseId": "CS-6300",
      "subject": "CS",
      "courseNumber": "6300",
      "name": "Software Dev Process",
      "creditHours": null,
      "sections": [
        {
          "crn": "26606",
          "sectionNumber": "O01",
          "instructor": "Orso, Alessandro",
          "enrolled": 394,
          "capacity": 400,
          "seatsAvailable": 6,
          "waitCount": 0,
          "waitCapacity": 500
        }
      ],
      "totalSeats": 400,
      "totalEnrolled": 394,
      "totalAvailable": 6,
      "totalWaitlisted": 0
    },
    "CS-6310": {
      "courseId": "CS-6310",
      "subject": "CS",
      "courseNumber": "6310",
      "name": "Software Arch &amp; Design",
      "creditHours": null,
      "sections": [
        {
          "crn": "27258",
          "sectionNumber": "O01",
          "instructor": "Moss, Mark",
          "enrolled": 339,
          "capacity": 458,
          "seatsAvailable": 119,
          "waitCount": 0,
          "waitCapacity": 500
        }
      ],
      "totalSeats": 458,
      "totalEnrolled": 339,
      "totalAvailable": 119,
      "totalWaitlisted": 0
    },
    "CS-6340": {
      "courseId": "CS-6340",
      "subject": "CS",
      "courseNumber": "6340",
      "name": "Software Analysis &amp; Test",
      "creditHours": null,
      "sections": [
        {
          "crn": "28334",
          "sectionNumber": "O01",
          "instructor": "Naik, Mayur",
          "enrolled": 240,
          "capacity": 300,
          "seatsAvailable": 60,
          "waitCount": 0,
          "waitCapacity": 500
        }
      ],
      "totalSeats": 300,
      "totalEnrolled": 240,
      "totalAvailable": 60,
      "totalWaitlisted": 0
    },
    "CS-6400": {
      "courseId": "CS-6400",
      "subject": "CS",
      "courseNumber": "6400",
      "name": "DB Sys Concepts&amp; Design",
      "creditHours": null,
      "sections": [
        {
          "crn": "28333",
          "sectionNumber": "O01",
          "instructor": "Mark, Leo",
          "enrolled": 432,
          "capacity": 475,
          "seatsAvailable": 43,
          "waitCount": 0,
          "waitCapacity": 500
        }
      ],
      "totalSeats": 475,
      "totalEnrolled": 432,
      "totalAvailable": 43,
      "totalWaitlisted": 0
    },
    "CS-6440": {
      "courseId": "CS-6440",
      "subject": "CS",
      "courseNumber": "6440",
      "name": "Intro Health Informatics",
      "creditHours": null,
      "sections": [
        {
          "crn": "31223",
          "sectionNumber": "O01",
          "instructor": "Braunstein, Mark",
          "enrolled": 259,
          "capacity": 201,
          "seatsAvailable": -58,
          "waitCount": 0,
          "waitCapacity": 500
        }
      ],
      "totalSeats": 201,
      "totalEnrolled": 259,
      "totalAvailable": -58,
      "totalWaitlisted": 0
    },
    "CS-6460": {
      "courseId": "CS-6460",
      "subject": "CS",
      "courseNumber": "6460",
      "name": "Educ Tech-Foundations",
      "creditHours": null,
      "sections": [
        {
          "crn": "28331",
          "sectionNumber": "O01",
          "instructor": "Joyner, David",
          "enrolled": 209,
          "capacity": 250,
          "seatsAvailable": 41,
          "waitCount": 0,
          "waitCapacity": 500
        }
      ],
      "totalSeats": 250,
      "totalEnrolled": 209,
      "totalAvailable": 41,
      "totalWaitlisted": 0
    },
    "CS-6475": {
      "courseId": "CS-6475",
      "subject": "CS",
      "courseNumber": "6475",
      "name": "Comp. Photography",
      "creditHours": null,
      "sections": [
        {
          "crn": "27262",
          "sectionNumber": "O01",
          "instructor": "Essa, Irfan",
          "enrolled": 290,
          "capacity": 350,
          "seatsAvailable": 60,
          "waitCount": 0,
          "waitCapacity": 500
        }
      ],
      "totalSeats": 350,
      "totalEnrolled": 290,
      "totalAvailable": 60,
      "totalWaitlisted": 0
    },
    "CS-6476": {
      "courseId": "CS-6476",
      "subject": "CS",
      "courseNumber": "6476",
      "name": "Computer Vision",
      "creditHours": null,
      "sections": [
        {
          "crn": "28329",
          "sectionNumber": "O01",
          "instructor": "Essa, Irfan",
          "enrolled": 288,
          "capacity": 375,
          "seatsAvailable": 87,
          "waitCount": 0,
          "waitCapacity": 500
        }
      ],
      "totalSeats": 375,
      "totalEnrolled": 288,
      "totalAvailable": 87,
      "totalWaitlisted": 0
    },
    "CS-6601": {
      "courseId": "CS-6601",
      "subject": "CS",
      "courseNumber": "6601",
      "name": "Artificial Intelligence",
      "creditHours": null,
      "sections": [
        {
          "crn": "28336",
          "sectionNumber": "O01",
          "instructor": "Starner, Thad",
          "enrolled": 425,
          "capacity": 500,
          "seatsAvailable": 75,
          "waitCount": 0,
          "waitCapacity": 500
        }
      ],
      "totalSeats": 500,
      "totalEnrolled": 425,
      "totalAvailable": 75,
      "totalWaitlisted": 0
    },
    "CS-6750": {
      "courseId": "CS-6750",
      "subject": "CS",
      "courseNumber": "6750",
      "name": "Human-Computer Interact",
      "creditHours": null,
      "sections": [
        {
          "crn": "29571",
          "sectionNumber": "O01",
          "instructor": "Joyner, David",
          "enrolled": 231,
          "capacity": 300,
          "seatsAvailable": 69,
          "waitCount": 0,
          "waitCapacity": 500
        }
      ],
      "totalSeats": 300,
      "totalEnrolled": 231,
      "totalAvailable": 69,
      "totalWaitlisted": 0
    },
    "CS-6999": {
      "courseId": "CS-6999",
      "subject": "CS",
      "courseNumber": "6999",
      "name": "Master&#39;s Project",
      "creditHours": null,
      "sections": [
        {
          "crn": "24964",
          "sectionNumber": "O02",
          "instructor": "Orso, Alessandro",
          "enrolled": 1,
          "capacity": 5,
          "seatsAvailable": 4,
          "waitCount": 0,
          "waitCapacity": 0
        }
      ],
      "totalSeats": 5,
      "totalEnrolled": 1,
      "totalAvailable": 4,
      "totalWaitlisted": 0
    },
    "CS-7637": {
      "courseId": "CS-7637",
      "subject": "CS",
      "courseNumber": "7637",
      "name": "Knowledge-Based AI",
      "creditHours": null,
      "sections": [
        {
          "crn": "27260",
          "sectionNumber": "O01",
          "instructor": "Goel, Ashok",
          "enrolled": 338,
          "capacity": 400,
          "seatsAvailable": 62,
          "waitCount": 0,
          "waitCapacity": 500
        }
      ],
      "totalSeats": 400,
      "totalEnrolled": 338,
      "totalAvailable": 62,
      "totalWaitlisted": 0
    },
    "CS-7641": {
      "courseId": "CS-7641",
      "subject": "CS",
      "courseNumber": "7641",
      "name": "Machine Learning",
      "creditHours": null,
      "sections": [
        {
          "crn": "26607",
          "sectionNumber": "O01",
          "instructor": "Isbell, Charles",
          "enrolled": 623,
          "capacity": 700,
          "seatsAvailable": 77,
          "waitCount": 0,
          "waitCapacity": 999
        }
      ],
      "totalSeats": 700,
      "totalEnrolled": 623,
      "totalAvailable": 77,
      "totalWaitlisted": 0
    },
    "CS-7642": {
      "courseId": "CS-7642",
      "subject": "CS",
      "courseNumber": "7642",
      "name": "Reinforcement Learning",
      "creditHours": null,
      "sections": [
        {
          "crn": "31262",
          "sectionNumber": "O03",
          "instructor": "Isbell, Charles",
          "enrolled": 303,
          "capacity": 400,
          "seatsAvailable": 97,
          "waitCount": 0,
          "waitCapacity": 500
        }
      ],
      "totalSeats": 400,
      "totalEnrolled": 303,
      "totalAvailable": 97,
      "totalWaitlisted": 0
    },
    "CS-7646": {
      "courseId": "CS-7646",
      "subject": "CS",
      "courseNumber": "7646",
      "name": "Mach Learn For Trading",
      "creditHours": null,
      "sections": [
        {
          "crn": "28327",
          "sectionNumber": "O01",
          "instructor": "Balch, Tucker",
          "enrolled": 597,
          "capacity": 600,
          "seatsAvailable": 3,
          "waitCount": 0,
          "waitCapacity": 999
        }
      ],
      "totalSeats": 600,
      "totalEnrolled": 597,
      "totalAvailable": 3,
      "totalWaitlisted": 0
    },
    "CS-8803-O01": {
      "courseId": "CS-8803-O01",
      "subject": "CS",
      "courseNumber": "8803-O01",
      "name": "Special Topics",
      "creditHours": null,
      "sections": [
        {
          "crn": "27261",
          "sectionNumber": "O01",
          "instructor": "Thrun, Sebastian",
          "enrolled": 304,
          "capacity": 357,
          "seatsAvailable": 53,
          "waitCount": 0,
          "waitCapacity": 500
        }
      ],
      "totalSeats": 357,
      "totalEnrolled": 304,
      "totalAvailable": 53,
      "totalWaitlisted": 0
    },
    "CS-8803-O07": {
      "courseId": "CS-8803-O07",
      "subject": "CS",
      "courseNumber": "8803-O07",
      "name": "Special Topics",
      "creditHours": null,
      "sections": [
        {
          "crn": "29570",
          "sectionNumber": "O07",
          "instructor": "Beyah, Raheem",
          "enrolled": 88,
          "capacity": 200,
          "seatsAvailable": 112,
          "waitCount": 0,
          "waitCapacity": 500
        }
      ],
      "totalSeats": 200,
      "totalEnrolled": 88,
      "totalAvailable": 112,
      "totalWaitlisted": 0
    },
    "CS-8803-O08": {
      "courseId": "CS-8803-O08",
      "subject": "CS",
      "courseNumber": "8803-O08",
      "name": "Special Topics",
      "creditHours": null,
      "sections": [
        {
          "crn": "29813",
          "sectionNumber": "O08",
          "instructor": "Pande, Santosh",
          "enrolled": 46,
          "capacity": 200,
          "seatsAvailable": 154,
          "waitCount": 0,
          "waitCapacity": 500
        }
      ],
      "totalSeats": 200,
      "totalEnrolled": 46,
      "totalAvailable": 154,
      "totalWaitlisted": 0
    },
    "CS-8803-O09": {
      "courseId": "CS-8803-O09",
      "subject": "CS",
      "courseNumber": "8803-O09",
      "name": "Special Topics",
      "creditHours": null,
      "sections": [
        {
          "crn": "31208",
          "sectionNumber": "O09",
          "instructor": "Feron, Eric",
          "enrolled": 30,
          "capacity": 200,
          "seatsAvailable": 170,
          "waitCount": 0,
          "waitCapacity": 500
        }
      ],
      "totalSeats": 200,
      "totalEnrolled": 30,
      "totalAvailable": 170,
      "totalWaitlisted": 0
    },
    "CS-8902": {
      "courseId": "CS-8902",
      "subject": "CS",
      "courseNumber": "8902",
      "name": "Special Problems",
      "creditHours": null,
      "sections": [
        {
          "crn": "21545",
          "sectionNumber": "O02",
          "instructor": "Orso, Alessandro",
          "enrolled": 0,
          "capacity": 15,
          "seatsAvailable": 15,
          "waitCount": 0,
          "waitCapacity": 0
        }
      ],
      "totalSeats": 15,
      "totalEnrolled": 0,
      "totalAvailable": 15,
      "totalWaitlisted": 0
    },
    "CS-8903": {
      "courseId": "CS-8903",
      "subject": "CS",
      "courseNumber": "8903",
      "name": "Special Problems",
      "creditHours": null,
      "sections": [
        {
          "crn": "21375",
          "sectionNumber": "O02",
          "instructor": "Orso, Alessandro",
          "enrolled": 1,
          "capacity": 15,
          "seatsAvailable": 14,
          "waitCount": 0,
          "waitCapacity": 0
        },
        {
          "crn": "21906",
          "sectionNumber": "O03",
          "instructor": "Owen, Henry",
          "enrolled": 0,
          "capacity": 15,
          "seatsAvailable": 15,
          "waitCount": 0,
          "waitCapacity": 0
        }
      ],
      "totalSeats": 30,
      "totalEnrolled": 1,
      "totalAvailable": 29,
      "totalWaitlisted": 0
    },
    "CS-8999": {
      "courseId": "CS-8999",
      "subject": "CS",
      "courseNumber": "8999",
      "name": "Doctoral Thesis Prep",
      "creditHours": null,
      "sections": [
        {
          "crn": "24126",
          "sectionNumber": "O02",
          "instructor": "Orso, Alessandro",
          "enrolled": 2,
          "capacity": 10,
          "seatsAvailable": 8,
          "waitCount": 0,
          "waitCapacity": 0
        }
      ],
      "totalSeats": 10,
      "totalEnrolled": 2,
      "totalAvailable": 8,
      "totalWaitlisted": 0
    },
    "CS-9000": {
      "courseId": "CS-9000",
      "subject": "CS",
      "courseNumber": "9000",
      "name": "Doctoral Thesis",
      "creditHours": null,
      "sections": [
        {
          "crn": "21380",
          "sectionNumber": "O02",
          "instructor": "Orso, Alessandro",
          "enrolled": 4,
          "capacity": 15,
          "seatsAvailable": 11,
          "waitCount": 0,
          "waitCapacity": 0
        }
      ],
      "totalSeats": 15,
      "totalEnrolled": 4,
      "totalAvailable": 11,
      "totalWaitlisted": 0
    },
    "ECE-8900": {
      "courseId": "ECE-8900",
      "subject": "ECE",
      "courseNumber": "8900",
      "name": "Special Problems",
      "creditHours": null,
      "sections": [
        {
          "crn": "22274",
          "sectionNumber": "O01",
          "instructor": "Owen, Henry",
          "enrolled": 0,
          "capacity": 25,
          "seatsAvailable": 25,
          "waitCount": 0,
          "waitCapacity": 0
        },
        {
          "crn": "22275",
          "sectionNumber": "O02",
          "instructor": "Ougazzaden, Abdallah",
          "enrolled": 0,
          "capacity": 10,
          "seatsAvailable": 10,
          "waitCount": 0,
          "waitCapacity": 0
        }
      ],
      "totalSeats": 35,
      "totalEnrolled": 0,
      "totalAvailable": 35,
      "totalWaitlisted": 0
    },
    "ECE-8903": {
      "courseId": "ECE-8903",
      "subject": "ECE",
      "courseNumber": "8903",
      "name": "Special Problems",
      "creditHours": 3,
      "sections": [
        {
          "crn": "20602",
          "sectionNumber": "O01",
          "instructor": "Owen, Henry",
          "enrolled": 0,
          "capacity": 15,
          "seatsAvailable": 15,
          "waitCount": 0,
          "waitCapacity": 0
        },
        {
          "crn": "24385",
          "sectionNumber": "O02",
          "instructor": "Ougazzaden, Abdallah",
          "enrolled": 0,
          "capacity": 25,
          "seatsAvailable": 25,
          "waitCount": 0,
          "waitCapacity": 0
        }
      ],
      "totalSeats": 40,
      "totalEnrolled": 0,
      "totalAvailable": 40,
      "totalWaitlisted": 0
    },
    "ECE-9000": {
      "courseId": "ECE-9000",
      "subject": "ECE",
      "courseNumber": "9000",
      "name": "Doctoral Thesis",
      "creditHours": null,
      "sections": [
        {
          "crn": "20520",
          "sectionNumber": "O01",
          "instructor": "Owen, Henry",
          "enrolled": 0,
          "capacity": 25,
          "seatsAvailable": 25,
          "waitCount": 0,
          "waitCapacity": 0
        },
        {
          "crn": "23129",
          "sectionNumber": "O02",
          "instructor": "Ougazzaden, Abdallah",
          "enrolled": 0,
          "capacity": 25,
          "seatsAvailable": 25,
          "waitCount": 0,
          "waitCapacity": 0
        }
      ],
      "totalSeats": 50,
      "totalEnrolled": 0,
      "totalAvailable": 50,
      "totalWaitlisted": 0
    }
  }
}